python_roc/__init__.py
python_roc/roc.py
python_roc-1.0.0.dist-info/WHEEL
python_roc-1.0.0.dist-info/METADATA
python_roc-1.0.0.dist-info/RECORD
