Metadata-Version: 2.1
Name: python-roc
Version: 1.0.0
Summary: ROC curve visualization tool
Author: Petro Liashchynskyi
Author-email: p.liashchynskyi@apiko.com
Requires-Python: >=3.6,<4.0
Classifier: Programming Language :: Python :: 3
Classifier: Programming Language :: Python :: 3.10
Classifier: Programming Language :: Python :: 3.6
Classifier: Programming Language :: Python :: 3.7
Classifier: Programming Language :: Python :: 3.8
Classifier: Programming Language :: Python :: 3.9
Requires-Dist: matplotlib (==3.3.4)
Requires-Dist: numpy (==1.19.5)
Requires-Dist: scipy (==1.1.0)
Requires-Dist: sklearn (>=0.0,<0.1)
